egile_mcp_starter/__init__.py
egile_mcp_starter/cli.py
egile_mcp_starter/generator.py
egile_mcp_starter/plugins/__init__.py
egile_mcp_starter/plugins/base.py
egile_mcp_starter/plugins/builtin/__init__.py
egile_mcp_starter/plugins/builtin/mcp_template.py
egile_mcp_starter/plugins/builtin/rag_template.py
egile_mcp_starter/plugins/registry.py
egile_mcp_starter/template/cookiecutter.json
egile_mcp_starter/template/{{cookiecutter.project_slug}}/.github/workflows/ci.yml
egile_mcp_starter/template/{{cookiecutter.project_slug}}/.gitignore
egile_mcp_starter/template/{{cookiecutter.project_slug}}/.pre-commit-config.yaml
egile_mcp_starter/template/{{cookiecutter.project_slug}}/Dockerfile
egile_mcp_starter/template/{{cookiecutter.project_slug}}/LICENSE
egile_mcp_starter/template/{{cookiecutter.project_slug}}/README.md
egile_mcp_starter/template/{{cookiecutter.project_slug}}/config.example.yaml
egile_mcp_starter/template/{{cookiecutter.project_slug}}/docker-compose.yml
egile_mcp_starter/template/{{cookiecutter.project_slug}}/pyproject.toml
egile_mcp_starter/template/{{cookiecutter.project_slug}}/src/main.py
egile_mcp_starter/template/{{cookiecutter.project_slug}}/src/{{cookiecutter.project_slug}}/__init__.py
egile_mcp_starter/template/{{cookiecutter.project_slug}}/src/{{cookiecutter.project_slug}}/config.py
egile_mcp_starter/template/{{cookiecutter.project_slug}}/src/{{cookiecutter.project_slug}}/prompts/__init__.py
egile_mcp_starter/template/{{cookiecutter.project_slug}}/src/{{cookiecutter.project_slug}}/prompts/example_prompts.py
egile_mcp_starter/template/{{cookiecutter.project_slug}}/src/{{cookiecutter.project_slug}}/resources/__init__.py
egile_mcp_starter/template/{{cookiecutter.project_slug}}/src/{{cookiecutter.project_slug}}/resources/example_resources.py
egile_mcp_starter/template/{{cookiecutter.project_slug}}/src/{{cookiecutter.project_slug}}/server.py
egile_mcp_starter/template/{{cookiecutter.project_slug}}/src/{{cookiecutter.project_slug}}/tools/__init__.py
egile_mcp_starter-0.2.0.dist-info/LICENSE
egile_mcp_starter-0.2.0.dist-info/METADATA
egile_mcp_starter-0.2.0.dist-info/WHEEL
egile_mcp_starter-0.2.0.dist-info/entry_points.txt
egile_mcp_starter-0.2.0.dist-info/RECORD
