Metadata-Version: 2.3
Name: egile-mcp-starter
Version: 0.2.0
Summary: A comprehensive and extensible cookiecutter template system for creating Model Context Protocol (MCP) servers with plugin architecture supporting multiple templates including RAG-enabled servers
Keywords: mcp,model-context-protocol,fastmcp,cookiecutter,template,ai,assistant,rag,retrieval-augmented-generation,vector-database,plugin-architecture,chroma,pinecone,faiss,embedding
Author: Jean-Baptiste Poullet
Author-email: egile@gmail.com
Requires-Python: >=3.10
Classifier: Development Status :: 4 - Beta
Classifier: Intended Audience :: Developers
Classifier: License :: OSI Approved :: MIT License
Classifier: Operating System :: OS Independent
Classifier: Programming Language :: Python :: 3
Classifier: Programming Language :: Python :: 3.10
Classifier: Programming Language :: Python :: 3.11
Classifier: Programming Language :: Python :: 3.12
Classifier: Topic :: Software Development :: Code Generators
Classifier: Topic :: Software Development :: Libraries :: Python Modules
Classifier: Topic :: Communications
Classifier: Topic :: Internet :: WWW/HTTP :: HTTP Servers
Requires-Dist: click (>=8.0.0)
Requires-Dist: cookiecutter (>=2.1.1)
Requires-Dist: jinja2 (>=3.0.0)
Requires-Dist: pyyaml (>=6.0)
Project-URL: Documentation, https://github.com/jpoullet2000/egile-mcp-starter
Project-URL: Homepage, https://github.com/jpoullet2000/egile-mcp-starter
Project-URL: Repository, https://github.com/jpoullet2000/egile-mcp-starter
